azurify/__init__.py
azurify/azconverter.py
azurify/azenv.py
azurify/azkeyvault.py
azurify/azsecrets.py
azurify/azstorage.py
azurify/test_azconverter.py
azurify/test_azkeyvault.py
azurify/test_azsecrets.py
azurify/test_azstorage.py
azurify-0.72.dist-info/LICENSE
azurify-0.72.dist-info/METADATA
azurify-0.72.dist-info/WHEEL
azurify-0.72.dist-info/top_level.txt
azurify-0.72.dist-info/RECORD
