Metadata-Version: 2.1
Name: azurify
Version: 0.72
Summary: Access to Azure Storage/Secrets/Keyvault for Shopify Apps built with Python.
Home-page: https://github.com/zinyosrim/azurify
Author: Zin Yosrim
Author-email: zinyosrim@gmail.com
License: MIT
Classifier: License :: OSI Approved :: MIT License
Classifier: Programming Language :: Python :: 3.10
Classifier: Operating System :: OS Independent
Requires-Python: >=3.9
License-File: LICENSE
Requires-Dist: pandas
Requires-Dist: StrEnum
Requires-Dist: azure-identity
Requires-Dist: azure-keyvault-secrets
Requires-Dist: azure-mgmt-keyvault
Requires-Dist: azure-mgmt-resource
Requires-Dist: azure-storage-blob
Provides-Extra: dev
Requires-Dist: unitest ; extra == 'dev'
Requires-Dist: twine ; extra == 'dev'
